Metadata-Version: 1.1
Name: opie
Version: 0.0.6
Summary: A helping friend for the OP-1 synthesizer.
Home-page: UNKNOWN
Author: Jake McGinty
Author-email: me@jake.su
License: UNKNOWN
Platform: UNKNOWN
Classifier: Development Status :: 3 - Alpha
Classifier: Topic :: Utilities
